LICENSE
README.md
pyproject.toml
setup.py
muben/__init__.py
muben.egg-info/PKG-INFO
muben.egg-info/SOURCES.txt
muben.egg-info/dependency_links.txt
muben.egg-info/not-zip-safe
muben.egg-info/top_level.txt
muben/args/__init__.py
muben/args/args.py
muben/args/args_2d.py
muben/args/args_3d.py
muben/args/args_grover.py
muben/args/args_linear.py
muben/args/args_rdkit.py
muben/args/args_unimol.py
muben/dataset/__init__.py
muben/dataset/dataset.py
muben/dataset/dataset_2d/__init__.py
muben/dataset/dataset_2d/collate.py
muben/dataset/dataset_2d/dataset.py
muben/dataset/dataset_3d/__init__.py
muben/dataset/dataset_3d/collate.py
muben/dataset/dataset_3d/dataset.py
muben/dataset/dataset_grover/__init__.py
muben/dataset/dataset_grover/collate.py
muben/dataset/dataset_grover/dataset.py
muben/dataset/dataset_grover/molgraph.py
muben/dataset/dataset_linear/__init__.py
muben/dataset/dataset_linear/collate.py
muben/dataset/dataset_linear/dataset.py
muben/dataset/dataset_rdkit/__init__.py
muben/dataset/dataset_rdkit/collate.py
muben/dataset/dataset_rdkit/dataset.py
muben/dataset/dataset_unimol/__init__.py
muben/dataset/dataset_unimol/collate.py
muben/dataset/dataset_unimol/dataset.py
muben/dataset/dataset_unimol/dictionary.py
muben/dataset/dataset_unimol/process.py
muben/layers/__init__.py
muben/layers/layers.py
muben/model/__init__.py
muben/model/dnn/__init__.py
muben/model/dnn/dnn.py
muben/model/gin/__init__.py
muben/model/gin/gin.py
muben/model/grover/__init__.py
muben/model/grover/layers.py
muben/model/grover/model.py
muben/model/grover/ts.py
muben/model/grover/utils.py
muben/model/linear_transformer/__init__.py
muben/model/linear_transformer/linear_transformer.py
muben/model/torchmdnet/__init__.py
muben/model/torchmdnet/et.py
muben/model/torchmdnet/layers.py
muben/model/torchmdnet/modules.py
muben/model/torchmdnet/torchmdnet.py
muben/model/unimol/__init__.py
muben/model/unimol/encoder.py
muben/model/unimol/module.py
muben/model/unimol/unimol.py
muben/model/unimol/layers/__init__.py
muben/model/unimol/layers/layer_norm.py
muben/model/unimol/layers/multihead_attention.py
muben/model/unimol/layers/softmax_dropout.py
