Metadata-Version: 2.1
Name: muben
Version: 0.0.2
Summary: Benchmark for molecular uncertainty estimation.
Home-page: https://github.com/Yinghao-Li/MUBen
Author: Yinghao Li
Author-email: yinghaoli@gatech.edu
License: MIT
Keywords: machine-learning uncertainty-estimation materials-science materials-property-prediction
Classifier: Intended Audience :: Developers
Classifier: Intended Audience :: Science/Research
Classifier: License :: OSI Approved :: Apache Software License
Classifier: Operating System :: OS Independent
Classifier: Programming Language :: Python :: 3
Classifier: Topic :: Text Processing
Classifier: Topic :: Text Processing :: Linguistic
Requires-Python: >=3.9
License-File: LICENSE
